impact_stack/rest/__init__.py
impact_stack/rest/exceptions.py
impact_stack/rest/rest.py
impact_stack/rest/utils.py
impact_stack_rest-0.3.1.dist-info/licenses/LICENSE
impact_stack_rest-0.3.1.dist-info/METADATA
impact_stack_rest-0.3.1.dist-info/WHEEL
impact_stack_rest-0.3.1.dist-info/top_level.txt
impact_stack_rest-0.3.1.dist-info/RECORD
