Metadata-Version: 2.4
Name: impact-stack-rest
Version: 0.3.1
Summary: REST API client classes for inter-services communication in Impact Stack.
Author-email: Roman Zimmermann <roman@more-onion.com>
License-File: LICENSE
Requires-Dist: requests
Provides-Extra: dev
Requires-Dist: black; extra == "dev"
Requires-Dist: django; extra == "dev"
Requires-Dist: flask; extra == "dev"
Requires-Dist: isort; extra == "dev"
Requires-Dist: pre-commit; extra == "dev"
Requires-Dist: pylint; extra == "dev"
Requires-Dist: pytest; extra == "dev"
Requires-Dist: pytest-cov; extra == "dev"
Requires-Dist: requests-mock; extra == "dev"
Requires-Dist: twine; extra == "dev"
Dynamic: license-file
